lib16inpind/__init__.py
lib16inpind/example.py
lib16inpind/lib16inpind_data.py
sm16inpind-1.1.5.dist-info/LICENSE
sm16inpind-1.1.5.dist-info/METADATA
sm16inpind-1.1.5.dist-info/WHEEL
sm16inpind-1.1.5.dist-info/top_level.txt
sm16inpind-1.1.5.dist-info/RECORD
