Metadata-Version: 2.1
Name: sm16inpind
Version: 1.1.5
Summary: Library to control 16inpind Automation Card
Home-page: https://sequentmicrosystems.com
Author: Sequent Microsystems
Author-email: olcitu@gmail.com
License: MIT
Keywords: industrial,raspberry-pi,automation,digital-inputs,optoisolated-inputs,industrial-automation,gpio,input-monitoring,raspberry,rpi
Classifier: Development Status :: 4 - Beta
Classifier: Intended Audience :: Developers
Classifier: Topic :: Software Development :: Build Tools
Classifier: License :: OSI Approved :: MIT License
Classifier: Programming Language :: Python :: 2.7
Classifier: Programming Language :: Python :: 3
Classifier: Programming Language :: Python :: 3.4
Classifier: Programming Language :: Python :: 3.5
Classifier: Programming Language :: Python :: 3.6
Classifier: Programming Language :: Python :: 3.7
License-File: LICENSE
Requires-Dist: smbus2
